Workbook

Sheet Instructions & Requirements
B2: DATA CLEANING & ANALYTICS PROJECT
B3: Company: ApexTech Solutions Inc. | Dataset: Q3 Sales & Subscriptions
B5: Overview & Scenario
B6: You are a Data Analyst at ApexTech Solutions. Management has provided a raw export of Q3 order transactions from multiple legacy systems. The dataset contains various data quality issues including missing values, incorrect formats, duplicate records, trailing whitespaces, inconsistent product categories, and bad date formatting. Your objective is to clean the dataset in a new tab, perform analytics, and answer the business questions below. Once complete, send the completed Excel file back for grading!
B8: Task List (Grading Criteria)
B9: Task | C9: Description & Instructions
B10: Task 1: Standardize Dates | C10: Convert all values in 'Order Date' to a uniform YYYY-MM-DD date format. Fix text-based or corrupted date formats.
B11: Task 2: Trim Whitespace | C11: Clean leading/trailing spaces in 'Customer Name', 'Region', and 'Product Category'.
B12: Task 3: Text Case & Formatting | C12: Standardize 'Region' to Proper Case (e.g., 'North America', 'Europe', 'Asia-Pacific').
B13: Task 4: Remove Duplicates | C13: Identify and remove exact duplicate order rows based on 'Order ID'.
B14: Task 5: Handle Missing Values | C14: For missing 'Unit Price' or 'Quantity', calculate them using 'Total Sales' where possible, or flag/fill appropriately.
B15: Task 6: Standardize Categories | C15: Fix typos and inconsistent naming in 'Product Category' (e.g., 'SaaS Tools', 'saas-tool', 'Software').
B16: Task 7: Calculate Total Revenue | C16: Ensure 'Total Sales' equals 'Quantity' * 'Unit Price' * (1 - 'Discount %'). Add a clean calculated column.
B17: Task 8: Summary Analytics | C17: Calculate Total Revenue, Average Order Value, Top Region by Revenue, and Total Units Sold.

Sheet Raw_Data_Messy
A1: Order ID | B1: Order Date | C1: Customer Name | D1: Customer Type | E1: Region | F1: Product Category | G1: Quantity | H1: Unit Price | I1: Discount % | J1: Total Sales
A2: ORD-1001 | B2: 46204 | C2: Acme Corp | D2: Enterprise | E2: north america | F2: SaaS Tools | G2: 10 | H2: 150 | I2: 0.05 | J2: 1425
A3: ORD-1002 | B3: 46205 | C3: Global Tech | D3: SMB | E3: Europe | F3: saas Tools | G3: 5 | H3: 200 | I3: 0 | J3: 1000
A4: ORD-1003 | B4: 46206 | C4: Apex Systems | D4: Enterprise | E4: NORTH AMERICA | F4: Hardware | G4: 2 | H4: 1200 | I4: 0.1 | J4: 2160
A5: ORD-1004 | B5: 46208 | C5: Beta LLC | D5: Consumer | E5: asia-pacific | F5: Cloud Hosting | G5: 15 | H5: 40 | I5: 0 | J5: 600
A6: ORD-1005 | B6: 46208 | C6: Delta Inc | D6: SMB | E6: Europe | F6: Cloud Hosting | G6: 8 | H6: N/A | I6: 0.05 | J6: 380
A7: ORD-1006 | B7: N/A | C7: Echo Media | D7: Consumer | E7: North America | F7: SaaS Tools | G7: 1 | H7: 300 | I7: 0 | J7: 300
A8: ORD-1001 | B8: 46204 | C8: Acme Corp | D8: Enterprise | E8: north america | F8: SaaS Tools | G8: 10 | H8: 150 | I8: 0.05 | J8: 1425
A9: ORD-1007 | B9: 46211 | C9: Foxtrot Logistics | D9: Enterprise | E9: EUROPE | F9: Hardware | G9: 10 | H9: 1100 | I9: 0.15 | J9: 9350
A10: ORD-1008 | B10: 46213 | C10: Gamma Partners | D10: SMB | E10: asia pacific | F10: SaaS | G10: 4 | H10: 250 | I10: 0 | J10: 1000
A11: ORD-1009 | B11: 46215 | C11: Helios Energy | D11: Enterprise | E11: North America | F11: Cloud Hosting | G11: UNKNOWN | H11: 80 | I11: 0 | J11: 800
A12: ORD-1010 | B12: 46218 | C12: Iota Software | D12: SMB | E12: europe | F12: hardware | G12: 3 | H12: 1500 | I12: 0.1 | J12: 4050
A13: ORD-1011 | B13: 46219 | C13: Kappa Retail | D13: Consumer | E13: South America | F13: Cloud Hosting | G13: 20 | H13: 25 | I13: 0 | J13: 500
A14: ORD-1012 | B14: 46221 | C14: Lambda Health | D14: Enterprise | E14: North America | F14: SaaS Tools | G14: 6 | H14: 450 | I14: 0.05 | J14: 2565
A15: ORD-1013 | B15: 46223 | C15: Omega Group | D15: SMB | E15: Europe | F15: Cloud Hosting | G15: 12 | H15: 60 | I15: 0.1 | J15: 648
A16: ORD-1014 | B16: 46225 | C16: Sigma Analytics | D16: Enterprise | E16: Asia-Pacific | F16: SaaS Tools | G16: 5 | H16: 500 | I16: 0 | J16: 2500
A17: ORD-1014 | B17: 46225 | C17: Sigma Analytics | D17: Enterprise | E17: Asia-Pacific | F17: SaaS Tools | G17: 5 | H17: 500 | I17: 0 | J17: 2500
A18: ORD-1015 | B18: 46228 | C18: Theta Design | D18: Consumer | E18: north america | F18: Hardware | G18: 1 | H18: 2200 | I18: 0.2 | J18: 1760
A19: ORD-1016 | B19: 46231 | C19: Zeta Financial | D19: Enterprise | E19: Europe | F19: Cloud Hosting | G19: 25 | H19: 90 | I19: 0.05 | J19: 2137.5
A20: ORD-1017 | B20: 46232 | C20: Vortex AI | D20: SMB | E20: Asia-Pacific | F20: SaaS Tools | G20: 8 | H20: 350 | I20: 0 | J20: 2800
A21: ORD-1018 | B21: 46233 | C21: Zenith Labs | D21: Enterprise | E21: North America | F21: Hardware | G21: 4 | H21: 1300 | I21: 0.1 | J21: 4680

Sheet Answer_Key_Internal
A1: Order ID | B1: Order Date | C1: Customer Name | D1: Customer Type | E1: Region | F1: Product Category | G1: Quantity | H1: Unit Price | I1: Discount % | J1: Total Revenue | K1: Total Sales
A2: =Raw_Data_Messy!A2 -> ORD-1001 | B2: =Raw_Data_Messy!B2 -> 46204 | C2: =PROPER(TRIM(Raw_Data_Messy!C2)) -> Acme Corp | D2: =PROPER(TRIM(Raw_Data_Messy!D2)) -> Enterprise | E2: =PROPER(TRIM(Raw_Data_Messy!E2)) -> North America | F2: =PROPER(TRIM(Raw_Data_Messy!F2)) -> Saas Tools | G2: =Raw_Data_Messy!G2 -> 10 | H2: =Raw_Data_Messy!H2 -> 150 | I2: =Raw_Data_Messy!I2 -> 0.05 | J2: =IFERROR(G2*H2,"N/A") -> 1500 | K2: =IFERROR(G2*H2,"N/A") -> 1500
A3: =Raw_Data_Messy!A3 -> ORD-1002 | B3: =Raw_Data_Messy!B3 -> 46205 | C3: =PROPER(TRIM(Raw_Data_Messy!C3)) -> Global Tech | D3: =PROPER(TRIM(Raw_Data_Messy!D3)) -> Smb | E3: =PROPER(TRIM(Raw_Data_Messy!E3)) -> Europe | F3: =PROPER(TRIM(Raw_Data_Messy!F3)) -> Saas Tools | G3: =Raw_Data_Messy!G3 -> 5 | H3: =Raw_Data_Messy!H3 -> 200 | I3: =Raw_Data_Messy!I3 -> 0 | J3: =IFERROR(G3*H3,"N/A") -> 1000 | K3: =IFERROR(G3*H3,"N/A") -> 1000
A4: =Raw_Data_Messy!A4 -> ORD-1003 | B4: =Raw_Data_Messy!B4 -> 46206 | C4: =PROPER(TRIM(Raw_Data_Messy!C4)) -> Apex Systems | D4: =PROPER(TRIM(Raw_Data_Messy!D4)) -> Enterprise | E4: =PROPER(TRIM(Raw_Data_Messy!E4)) -> North America | F4: =PROPER(TRIM(Raw_Data_Messy!F4)) -> Hardware | G4: =Raw_Data_Messy!G4 -> 2 | H4: =Raw_Data_Messy!H4 -> 1200 | I4: =Raw_Data_Messy!I4 -> 0.1 | J4: =IFERROR(G4*H4,"N/A") -> 2400 | K4: =IFERROR(G4*H4,"N/A") -> 2400
A5: =Raw_Data_Messy!A5 -> ORD-1004 | B5: =Raw_Data_Messy!B5 -> 46208 | C5: =PROPER(TRIM(Raw_Data_Messy!C5)) -> Beta Llc | D5: =PROPER(TRIM(Raw_Data_Messy!D5)) -> Consumer | E5: =PROPER(TRIM(Raw_Data_Messy!E5)) -> Asia-Pacific | F5: =PROPER(TRIM(Raw_Data_Messy!F5)) -> Cloud Hosting | G5: =Raw_Data_Messy!G5 -> 15 | H5: =Raw_Data_Messy!H5 -> 40 | I5: =Raw_Data_Messy!I5 -> 0 | J5: =IFERROR(G5*H5,"N/A") -> 600 | K5: =IFERROR(G5*H5,"N/A") -> 600
A6: =Raw_Data_Messy!A6 -> ORD-1005 | B6: =Raw_Data_Messy!B6 -> 46208 | C6: =PROPER(TRIM(Raw_Data_Messy!C6)) -> Delta Inc | D6: =PROPER(TRIM(Raw_Data_Messy!D6)) -> Smb | E6: =PROPER(TRIM(Raw_Data_Messy!E6)) -> Europe | F6: =PROPER(TRIM(Raw_Data_Messy!F6)) -> Cloud Hosting | G6: =Raw_Data_Messy!G6 -> 8 | H6: =Raw_Data_Messy!H6 -> N/A | I6: =Raw_Data_Messy!I6 -> 0.05 | J6: =IFERROR(G6*H6,"N/A") -> N/A | K6: =IFERROR(G6*H6,"N/A") -> N/A
A7: =Raw_Data_Messy!A7 -> ORD-1006 | B7: =Raw_Data_Messy!B7 -> N/A | C7: =PROPER(TRIM(Raw_Data_Messy!C7)) -> Echo Media | D7: =PROPER(TRIM(Raw_Data_Messy!D7)) -> Consumer | E7: =PROPER(TRIM(Raw_Data_Messy!E7)) -> North America | F7: =PROPER(TRIM(Raw_Data_Messy!F7)) -> Saas Tools | G7: =Raw_Data_Messy!G7 -> 1 | H7: =Raw_Data_Messy!H7 -> 300 | I7: =Raw_Data_Messy!I7 -> 0 | J7: =IFERROR(G7*H7,"N/A") -> 300 | K7: =IFERROR(G7*H7,"N/A") -> 300
A8: =Raw_Data_Messy!A9 -> ORD-1007 | B8: =Raw_Data_Messy!B8 -> 46204 | C8: =PROPER(TRIM(Raw_Data_Messy!C8)) -> Acme Corp | D8: =PROPER(TRIM(Raw_Data_Messy!D8)) -> Enterprise | E8: =PROPER(TRIM(Raw_Data_Messy!E8)) -> North America | F8: =PROPER(TRIM(Raw_Data_Messy!F8)) -> Saas Tools | G8: =Raw_Data_Messy!G8 -> 10 | H8: =Raw_Data_Messy!H8 -> 150 | I8: =Raw_Data_Messy!I8 -> 0.05 | J8: =IFERROR(G8*H8,"N/A") -> 1500 | K8: =IFERROR(G8*H8,"N/A") -> 1500
A9: =Raw_Data_Messy!A10 -> ORD-1008 | B9: =Raw_Data_Messy!B9 -> 46211 | C9: =PROPER(TRIM(Raw_Data_Messy!C9)) -> Foxtrot Logistics | D9: =PROPER(TRIM(Raw_Data_Messy!D9)) -> Enterprise | E9: =PROPER(TRIM(Raw_Data_Messy!E9)) -> Europe | F9: =PROPER(TRIM(Raw_Data_Messy!F9)) -> Hardware | G9: =Raw_Data_Messy!G9 -> 10 | H9: =Raw_Data_Messy!H9 -> 1100 | I9: =Raw_Data_Messy!I9 -> 0.15 | J9: =IFERROR(G9*H9,"N/A") -> 11000 | K9: =IFERROR(G9*H9,"N/A") -> 11000
A10: =Raw_Data_Messy!A11 -> ORD-1009 | B10: =Raw_Data_Messy!B10 -> 46213 | C10: =PROPER(TRIM(Raw_Data_Messy!C10)) -> Gamma Partners | D10: =PROPER(TRIM(Raw_Data_Messy!D10)) -> Smb | E10: =PROPER(TRIM(Raw_Data_Messy!E10)) -> Asia Pacific | F10: =PROPER(TRIM(Raw_Data_Messy!F10)) -> Saas | G10: =Raw_Data_Messy!G10 -> 4 | H10: =Raw_Data_Messy!H10 -> 250 | I10: =Raw_Data_Messy!I10 -> 0 | J10: =IFERROR(G10*H10,"N/A") -> 1000 | K10: =IFERROR(G10*H10,"N/A") -> 1000
A11: =Raw_Data_Messy!A12 -> ORD-1010 | B11: =Raw_Data_Messy!B11 -> 46215 | C11: =PROPER(TRIM(Raw_Data_Messy!C11)) -> Helios Energy | D11: =PROPER(TRIM(Raw_Data_Messy!D11)) -> Enterprise | E11: =PROPER(TRIM(Raw_Data_Messy!E11)) -> North America | F11: =PROPER(TRIM(Raw_Data_Messy!F11)) -> Cloud Hosting | G11: N/A | H11: =Raw_Data_Messy!H11 -> 80 | I11: =Raw_Data_Messy!I11 -> 0 | J11: =IFERROR(G11*H11,"N/A") -> N/A | K11: =IFERROR(G11*H11,"N/A") -> N/A
A12: =Raw_Data_Messy!A13 -> ORD-1011 | B12: =Raw_Data_Messy!B12 -> 46218 | C12: =PROPER(TRIM(Raw_Data_Messy!C12)) -> Iota Software | D12: =PROPER(TRIM(Raw_Data_Messy!D12)) -> Smb | E12: =PROPER(TRIM(Raw_Data_Messy!E12)) -> Europe | F12: =PROPER(TRIM(Raw_Data_Messy!F12)) -> Hardware | G12: =Raw_Data_Messy!G12 -> 3 | H12: =Raw_Data_Messy!H12 -> 1500 | I12: =Raw_Data_Messy!I12 -> 0.1 | J12: =IFERROR(G12*H12,"N/A") -> 4500 | K12: =IFERROR(G12*H12,"N/A") -> 4500
A13: =Raw_Data_Messy!A14 -> ORD-1012 | B13: =Raw_Data_Messy!B13 -> 46219 | C13: =PROPER(TRIM(Raw_Data_Messy!C13)) -> Kappa Retail | D13: =PROPER(TRIM(Raw_Data_Messy!D13)) -> Consumer | E13: =PROPER(TRIM(Raw_Data_Messy!E13)) -> South America | F13: =PROPER(TRIM(Raw_Data_Messy!F13)) -> Cloud Hosting | G13: =Raw_Data_Messy!G13 -> 20 | H13: =Raw_Data_Messy!H13 -> 25 | I13: =Raw_Data_Messy!I13 -> 0 | J13: =IFERROR(G13*H13,"N/A") -> 500 | K13: =IFERROR(G13*H13,"N/A") -> 500
A14: =Raw_Data_Messy!A15 -> ORD-1013 | B14: =Raw_Data_Messy!B14 -> 46221 | C14: =PROPER(TRIM(Raw_Data_Messy!C14)) -> Lambda Health | D14: =PROPER(TRIM(Raw_Data_Messy!D14)) -> Enterprise | E14: =PROPER(TRIM(Raw_Data_Messy!E14)) -> North America | F14: =PROPER(TRIM(Raw_Data_Messy!F14)) -> Saas Tools | G14: =Raw_Data_Messy!G14 -> 6 | H14: =Raw_Data_Messy!H14 -> 450 | I14: =Raw_Data_Messy!I14 -> 0.05 | J14: =IFERROR(G14*H14,"N/A") -> 2700 | K14: =IFERROR(G14*H14,"N/A") -> 2700
A15: =Raw_Data_Messy!A16 -> ORD-1014 | B15: =Raw_Data_Messy!B15 -> 46223 | C15: =PROPER(TRIM(Raw_Data_Messy!C15)) -> Omega Group | D15: =PROPER(TRIM(Raw_Data_Messy!D15)) -> Smb | E15: =PROPER(TRIM(Raw_Data_Messy!E15)) -> Europe | F15: =PROPER(TRIM(Raw_Data_Messy!F15)) -> Cloud Hosting | G15: =Raw_Data_Messy!G15 -> 12 | H15: =Raw_Data_Messy!H15 -> 60 | I15: =Raw_Data_Messy!I15 -> 0.1 | J15: =IFERROR(G15*H15,"N/A") -> 720 | K15: =IFERROR(G15*H15,"N/A") -> 720
A16: =Raw_Data_Messy!A18 -> ORD-1015 | B16: =Raw_Data_Messy!B16 -> 46225 | C16: =PROPER(TRIM(Raw_Data_Messy!C16)) -> Sigma Analytics | D16: =PROPER(TRIM(Raw_Data_Messy!D16)) -> Enterprise | E16: =PROPER(TRIM(Raw_Data_Messy!E16)) -> Asia-Pacific | F16: =PROPER(TRIM(Raw_Data_Messy!F16)) -> Saas Tools | G16: =Raw_Data_Messy!G16 -> 5 | H16: =Raw_Data_Messy!H16 -> 500 | I16: =Raw_Data_Messy!I16 -> 0 | J16: =IFERROR(G16*H16,"N/A") -> 2500 | K16: =IFERROR(G16*H16,"N/A") -> 2500
A17: =Raw_Data_Messy!A19 -> ORD-1016 | B17: =Raw_Data_Messy!B17 -> 46225 | C17: =PROPER(TRIM(Raw_Data_Messy!C17)) -> Sigma Analytics | D17: =PROPER(TRIM(Raw_Data_Messy!D17)) -> Enterprise | E17: =PROPER(TRIM(Raw_Data_Messy!E17)) -> Asia-Pacific | F17: =PROPER(TRIM(Raw_Data_Messy!F17)) -> Saas Tools | G17: =Raw_Data_Messy!G17 -> 5 | H17: =Raw_Data_Messy!H17 -> 500 | I17: =Raw_Data_Messy!I17 -> 0 | J17: =IFERROR(G17*H17,"N/A") -> 2500 | K17: =IFERROR(G17*H17,"N/A") -> 2500
A18: =Raw_Data_Messy!A20 -> ORD-1017 | B18: =Raw_Data_Messy!B18 -> 46228 | C18: =PROPER(TRIM(Raw_Data_Messy!C18)) -> Theta Design | D18: =PROPER(TRIM(Raw_Data_Messy!D18)) -> Consumer | E18: =PROPER(TRIM(Raw_Data_Messy!E18)) -> North America | F18: =PROPER(TRIM(Raw_Data_Messy!F18)) -> Hardware | G18: =Raw_Data_Messy!G18 -> 1 | H18: =Raw_Data_Messy!H18 -> 2200 | I18: =Raw_Data_Messy!I18 -> 0.2 | J18: =IFERROR(G18*H18,"N/A") -> 2200 | K18: =IFERROR(G18*H18,"N/A") -> 2200
A19: =Raw_Data_Messy!A21 -> ORD-1018 | B19: =Raw_Data_Messy!B19 -> 46231 | C19: =PROPER(TRIM(Raw_Data_Messy!C19)) -> Zeta Financial | D19: =PROPER(TRIM(Raw_Data_Messy!D19)) -> Enterprise | E19: =PROPER(TRIM(Raw_Data_Messy!E19)) -> Europe | F19: =PROPER(TRIM(Raw_Data_Messy!F19)) -> Cloud Hosting | G19: =Raw_Data_Messy!G19 -> 25 | H19: =Raw_Data_Messy!H19 -> 90 | I19: =Raw_Data_Messy!I19 -> 0.05 | J19: =IFERROR(G19*H19,"N/A") -> 2250 | K19: =IFERROR(G19*H19,"N/A") -> 2250
B20: =Raw_Data_Messy!B20 -> 46232 | C20: =Raw_Data_Messy!C20 -> Vortex AI | D20: =PROPER(TRIM(Raw_Data_Messy!D20)) -> Smb | E20: =PROPER(TRIM(Raw_Data_Messy!E20)) -> Asia-Pacific | F20: =PROPER(TRIM(Raw_Data_Messy!F20)) -> Saas Tools | G20: =Raw_Data_Messy!G20 -> 8 | H20: =Raw_Data_Messy!H20 -> 350 | I20: =Raw_Data_Messy!I20 -> 0 | J20: =IFERROR(G20*H20,"N/A") -> 2800 | K20: =IFERROR(G20*H20,"N/A") -> 2800
B21: =Raw_Data_Messy!B21 -> 46233 | C21: =PROPER(TRIM(Raw_Data_Messy!C21)) -> Zenith Labs | D21: =PROPER(TRIM(Raw_Data_Messy!D21)) -> Enterprise | E21: =PROPER(TRIM(Raw_Data_Messy!E21)) -> North America | F21: =PROPER(TRIM(Raw_Data_Messy!F21)) -> Hardware | G21: =Raw_Data_Messy!G21 -> 4 | H21: =Raw_Data_Messy!H21 -> 1300 | I21: =Raw_Data_Messy!I21 -> 0.1 | J21: =IFERROR(G21*H21,"N/A") -> 5200 | K21: =IFERROR(G21*H21,"N/A") -> 5200
A23: =CONCATENATE("Average Order Value : ",SUM($J$2:$J$21)/COUNT($G$2:$G$21)) -> Average Order Value : 2657.05882352941
A26: Region | B26: Sum of Total Revenue
A27: Asia Pacific | B27: 1000
A28: Asia-Pacific | B28: 8400
A29: Europe | B29: 19470
A30: North America | B30: 15800
A31: South America | B31: 500
A32: Grand Total | B32: 45170
